biobb_cmip/__init__.py
biobb_cmip/py.typed
biobb_cmip/cmip/__init__.py
biobb_cmip/cmip/cmip_ignore_residues.py
biobb_cmip/cmip/cmip_prepare_pdb.py
biobb_cmip/cmip/cmip_prepare_structure.py
biobb_cmip/cmip/cmip_run.py
biobb_cmip/cmip/cmip_titration.py
biobb_cmip/cmip/common.py
biobb_cmip/cmip/dat/aa.lib
biobb_cmip/cmip/dat/nuc.lib
biobb_cmip/cmip/dat/solv.vdwprm
biobb_cmip/cmip/dat/vdwprm
biobb_cmip/test/__init__.py
biobb_cmip/utils/__init__.py
biobb_cmip/utils/representation.py
biobb_cmip-5.2.0.dist-info/licenses/LICENSE
biobb_cmip-5.2.0.dist-info/METADATA
biobb_cmip-5.2.0.dist-info/WHEEL
biobb_cmip-5.2.0.dist-info/entry_points.txt
biobb_cmip-5.2.0.dist-info/top_level.txt
biobb_cmip-5.2.0.dist-info/RECORD
